pytest_black.py
pytest_black_ng-0.4.1.dist-info/LICENSE
pytest_black_ng-0.4.1.dist-info/METADATA
pytest_black_ng-0.4.1.dist-info/WHEEL
pytest_black_ng-0.4.1.dist-info/entry_points.txt
pytest_black_ng-0.4.1.dist-info/top_level.txt
pytest_black_ng-0.4.1.dist-info/RECORD
