Metadata-Version: 2.1
Name: pytest-black-ng
Version: 0.4.1
Summary: A pytest plugin to enable format checking with black
Home-page: https://github.com/insertjokehere/pytest-black-ng
Author: Will Hughes
Author-email: will@willhughes.name
Maintainer: Will Hughes
Maintainer-email: will@willhughes.name
License: MIT
Classifier: Development Status :: 4 - Beta
Classifier: Framework :: Pytest
Classifier: Intended Audience :: Developers
Classifier: Topic :: Software Development :: Testing
Classifier: Programming Language :: Python :: 3
Classifier: Operating System :: OS Independent
Classifier: License :: OSI Approved :: MIT License
Requires-Python: >=3.5
License-File: LICENSE
Requires-Dist: black (>=22.1.0)
Requires-Dist: pytest (>=7.0.0)
Requires-Dist: toml
